Metadata-Version: 1.1
Name: SerpentAI
Version: 2018.1.0
Summary: Game Agent Development Kit. Helping you create AIs / Bots to play any game you own!
Home-page: https://github.com/SerpentAI/Serpent
Author: Nicholas Brochu
Author-email: nicholas@serpent.ai
License: MIT
Platform: UNKNOWN
Classifier: Development Status :: 5 - Production/Stable
Classifier: Intended Audience :: Developers
Classifier: Intended Audience :: Science/Research
Classifier: Natural Language :: English
Classifier: License :: OSI Approved :: MIT License
Classifier: Operating System :: OS Independent
Classifier: Programming Language :: Python
Classifier: Programming Language :: Python :: 3.6
Classifier: Topic :: Software Development :: Libraries :: Application Frameworks
Classifier: Topic :: Scientific/Engineering :: Artificial Intelligence
Classifier: Topic :: Games/Entertainment
